<?xml version="1.0" encoding="UTF-8"?>
<ant previd="c3555" nextid="c3557" id="c3556">
   <header>
      <usage ms="Alb2" code="07062000">[106r] lauds</usage>
      <usage ms="Cdm" code="07062000">[76r] lauds-a5</usage>
      <usage ms="Cht" code="07062000">[57r] lauds</usage>
      <usage ms="Ely" code="07062000">[87r] lauds</usage>
      <usage ms="Evm" code="07062000">[144v] lauds</usage>
      <usage ms="Hyd" code="07062000">[92r] lauds</usage>
      <usage ms="Mch" code="07062000">[156r] lauds-a5</usage>
      <usage ms="Wcb" code="07062000">[113v] lauds</usage>
      <usage ms="Wor" code="07062000">[57r] lauds-a5</usage>
   </header>
   <aBody wit="CAO-C CAO-G CAO-B CAO-E CAO-M CAO-V CAO-H CAO-R CAO-D CAO-F CAO-S CAO-L Ely Wor Cht Hyd Evm Wcb Alb2 Cdm Mch"> Labia insurgentium
     <app>
         <rdg wit="CAO-C CAO-G CAO-B CAO-E CAO-M CAO-V CAO-H CAO-R CAO-D CAO-F CAO-S CAO-L Ely Wor Cht Evm Wcb Alb2 Cdm Mch"> et cogitationes eorum</rdg>
         <rdg wit="Hyd"> et cogitationes <add place="interlined" hand="scribe">eorum</add>
         </rdg>
      </app> vide domine</aBody>
</ant>