<?xml version="1.0" encoding="UTF-8"?>
<res previd="c6299" nextid="c6301" id="c6300">
   <rBody wit="CAO-H CAO-R CAO-L"> Cogitavi dies antiquos et annos aeternos in mente habui et meditatus sum nocte cum corde meo et dixi miserere Deus</rBody>
   <verses>
      <vBody type="r" wit="CAO-H CAO-R"> Illuxerunt coruscationes tuae orbi terrae vidit et commota est terra</vBody>
      <vBody type="r" wit="CAO-L"> In die tribulationis meae Deum exquisivi manibus meis nocte coram eo</vBody>
      <rep type="r" wit="CAO-H CAO-R CAO-L">Et dixi</rep>
   </verses>
</res>