<?xml version="1.0" encoding="UTF-8"?>
<res previd="c7899" nextid="c7901" id="c7900">
   <rBody wit="CAO-R"> Vir vitae laudabilis postquam in ordine clericatus quatuor annis est deo hominibusque probatus artioris propositi desiderio accensus in insula Rheni fluminis monasticae perfectionis normam praesentibus initiavit et futuris</rBody>
   <verses>
      <vBody type="r" wit="CAO-R">Passer invenit sibi domum et turtur nidum sibi ubi reponat pullos suos</vBody>
      <rep type="r" wit="CAO-R">In insula</rep>
   </verses>
</res>